<fest:template xmlns:fest="http://fest.mail.ru" context_name="json">
	<div id = "header"> Space Hockey</div>
	<div class = "container">
			<h1>Login</h1>

        <form method="post" action="/api/v1/auth/signin">
            <div class = "form_div"><input  type="text"     class = "form_div_input"  name="login" /></div>
            <div class = "form_div"><input  type="password" class = "form_div_input" name="password" /></div>
            <div class = "form_div"><button type="submit"   class = "btn btn-primary" >GO!</button></div>
        </form>
   
	</div>
	<a href="#main" class="btn btn-primary">Back to the Future</a>
</fest:template>

